[
  {
    "name": "Vienna Lungo",
    "type": "Original",
    "image": "vienna-lungo.jpg"
  },
  {
    "name": "Stockholm Lungo",
    "type": "Original",
    "image": "stockholm-lungo.jpg"
  },
  {
    "name": "Cape Town Lungo",
    "type": "Original",
    "image": "capetown-lungo.jpg"
  },
  {
    "name": "Shanghai Lungo",
    "type": "Original",
    "image": "shanghai-lungo.jpg"
  },
  {
    "name": "Tokyo Lungo",
    "type": "Original",
    "image": "tokyo-lungo.jpg"
  },
  {
    "name": "Paris Espresso",
    "type": "Original",
    "image": "paris-espresso.jpg"
  }
  
]